django_excel_fixture/__init__.py
django_excel_fixture/serializers/__init__.py
django_excel_fixture/serializers/xlsx_serializer.py
django_excel_fixture-0.1.dist-info/LICENSE
django_excel_fixture-0.1.dist-info/METADATA
django_excel_fixture-0.1.dist-info/WHEEL
django_excel_fixture-0.1.dist-info/top_level.txt
django_excel_fixture-0.1.dist-info/zip-safe
django_excel_fixture-0.1.dist-info/RECORD
