Metadata-Version: 2.1
Name: django-excel-fixture
Version: 0.1
Summary: Django: import data, export data and test using xlsx files.
Home-page: http://github.com/portela/django-excel-fixture
Author: Henrique Portela, SKisContent
Author-email: henrique.portela@gmail.com
License: MIT
Platform: any
Classifier: Development Status :: 5 - Production/Stable
Classifier: Framework :: Django
Classifier: Intended Audience :: Developers
Classifier: License :: OSI Approved :: MIT License
Classifier: Natural Language :: English
Classifier: Operating System :: OS Independent
Classifier: Programming Language :: Python
Classifier: Programming Language :: Python :: 3
Classifier: Topic :: Software Development :: Libraries
